oneiric/__init__.py
oneiric/cli.py
oneiric/demo.py
oneiric/plugins.py
oneiric/actions/__init__.py
oneiric/actions/automation.py
oneiric/actions/bootstrap.py
oneiric/actions/bridge.py
oneiric/actions/compression.py
oneiric/actions/data.py
oneiric/actions/debug.py
oneiric/actions/event.py
oneiric/actions/http.py
oneiric/actions/metadata.py
oneiric/actions/payloads.py
oneiric/actions/security.py
oneiric/actions/serialization.py
oneiric/actions/task.py
oneiric/actions/workflow.py
oneiric/adapters/__init__.py
oneiric/adapters/bootstrap.py
oneiric/adapters/bridge.py
oneiric/adapters/httpx_base.py
oneiric/adapters/metadata.py
oneiric/adapters/metrics.py
oneiric/adapters/watcher.py
oneiric/adapters/cache/__init__.py
oneiric/adapters/cache/memory.py
oneiric/adapters/cache/redis.py
oneiric/adapters/database/__init__.py
oneiric/adapters/database/duckdb.py
oneiric/adapters/database/mysql.py
oneiric/adapters/database/postgres.py
oneiric/adapters/database/sqlite.py
oneiric/adapters/dns/__init__.py
oneiric/adapters/dns/cloudflare.py
oneiric/adapters/dns/gcdns.py
oneiric/adapters/dns/route53.py
oneiric/adapters/embedding/__init__.py
oneiric/adapters/embedding/common.py
oneiric/adapters/embedding/onnx.py
oneiric/adapters/embedding/openai.py
oneiric/adapters/embedding/sentence_transformers.py
oneiric/adapters/file_transfer/__init__.py
oneiric/adapters/file_transfer/ftp.py
oneiric/adapters/file_transfer/http_artifact.py
oneiric/adapters/file_transfer/http_upload.py
oneiric/adapters/file_transfer/scp.py
oneiric/adapters/file_transfer/sftp.py
oneiric/adapters/graph/__init__.py
oneiric/adapters/graph/arangodb.py
oneiric/adapters/graph/duckdb_pgq.py
oneiric/adapters/graph/neo4j.py
oneiric/adapters/http/__init__.py
oneiric/adapters/http/aiohttp.py
oneiric/adapters/http/httpx.py
oneiric/adapters/identity/__init__.py
oneiric/adapters/identity/auth0.py
oneiric/adapters/llm/__init__.py
oneiric/adapters/llm/anthropic.py
oneiric/adapters/llm/common.py
oneiric/adapters/llm/openai.py
oneiric-0.5.1.dist-info/licenses/LICENSE
oneiric-0.5.1.dist-info/METADATA
oneiric-0.5.1.dist-info/WHEEL
oneiric-0.5.1.dist-info/entry_points.txt
oneiric-0.5.1.dist-info/top_level.txt
oneiric-0.5.1.dist-info/RECORD
