Metadata-Version: 2.4
Name: oneiric
Version: 0.5.1
Summary: Universal resolution layer for pluggable components with hot-swapping and remote manifest delivery
Project-URL: ONNXRuntime-Compatibility, https://github.com/microsoft/onnxruntime/issues/new
Requires-Python: >=3.13
License-File: LICENSE
Requires-Dist: pydantic>=2.12.5
Requires-Dist: structlog>=25.5.0
Requires-Dist: opentelemetry-api>=1.38.0
Requires-Dist: pyyaml>=6.0.3
Requires-Dist: typer>=0.20.0
Requires-Dist: cryptography>=46.0.3
Requires-Dist: google-cloud-storage>=3.6.0
Requires-Dist: google-cloud-secret-manager>=2.25.0
Requires-Dist: email-validator>=2.2.0
Requires-Dist: numpy>=1.26.0
Requires-Dist: tenacity>=9.1.0
Requires-Dist: aiobreaker>=1.2.0
Requires-Dist: watchfiles>=1.1.0
Requires-Dist: anyio>=4.6.0
Requires-Dist: msgspec>=0.18.6
Requires-Dist: networkx>=3.2.0
Requires-Dist: ipython>=8.0.0
Provides-Extra: dev
Requires-Dist: pytest>=9.0.1; extra == "dev"
Requires-Dist: pytest-asyncio>=1.3.0; extra == "dev"
Requires-Dist: pytest-cov>=7.0.0; extra == "dev"
Requires-Dist: pytest-timeout>=2.4.0; extra == "dev"
Requires-Dist: pytest-benchmark>=4.0.0; extra == "dev"
Requires-Dist: freezegun>=1.5.5; extra == "dev"
Requires-Dist: uv-bump>=0.3.1; extra == "dev"
Requires-Dist: crackerjack>=0.45.2; extra == "dev"
Requires-Dist: session-buddy>=0.10.0; extra == "dev"
Requires-Dist: filelock>=3.20.1; extra == "dev"
Requires-Dist: zensical>=0.0.15; extra == "dev"
Requires-Dist: onnxruntime<1.24; extra == "dev"
Provides-Extra: cache
Requires-Dist: coredis>=5.3.0; extra == "cache"
Provides-Extra: database
Requires-Dist: asyncpg>=0.31.0; extra == "database"
Requires-Dist: aiomysql>=0.3.2; extra == "database"
Requires-Dist: aiosqlite>=0.21.0; extra == "database"
Provides-Extra: database-postgres
Requires-Dist: asyncpg>=0.31.0; extra == "database-postgres"
Provides-Extra: database-mysql
Requires-Dist: aiomysql>=0.3.2; extra == "database-mysql"
Provides-Extra: database-sqlite
Requires-Dist: aiosqlite>=0.21.0; extra == "database-sqlite"
Provides-Extra: http-aiohttp
Requires-Dist: aiohttp>=3.13.2; extra == "http-aiohttp"
Provides-Extra: identity-auth0
Requires-Dist: PyJWT>=2.8; extra == "identity-auth0"
Provides-Extra: dns
Requires-Dist: google-cloud-dns>=0.35.0; extra == "dns"
Provides-Extra: dns-gcdns
Requires-Dist: google-cloud-dns>=0.35.0; extra == "dns-gcdns"
Provides-Extra: monitoring
Requires-Dist: opentelemetry-exporter-otlp>=1.38.0; extra == "monitoring"
Requires-Dist: opentelemetry-sdk>=1.38.0; extra == "monitoring"
Requires-Dist: sentry-sdk>=3.0.0a7; extra == "monitoring"
Provides-Extra: monitoring-logfire
Requires-Dist: logfire>=4.15.1; extra == "monitoring-logfire"
Provides-Extra: monitoring-otlp
Requires-Dist: opentelemetry-exporter-otlp>=1.38.0; extra == "monitoring-otlp"
Requires-Dist: opentelemetry-sdk>=1.38.0; extra == "monitoring-otlp"
Provides-Extra: monitoring-sentry
Requires-Dist: sentry-sdk>=3.0.0a7; extra == "monitoring-sentry"
Provides-Extra: monitoring-netdata
Requires-Dist: httpx>=0.27.2; extra == "monitoring-netdata"
Provides-Extra: queue-nats
Requires-Dist: nats-py>=2.12.0; extra == "queue-nats"
Provides-Extra: storage
Requires-Dist: aioboto3>=15.5.0; extra == "storage"
Requires-Dist: azure-storage-blob>=12.27.1; extra == "storage"
Provides-Extra: storage-azure
Requires-Dist: azure-storage-blob>=12.27.1; extra == "storage-azure"
Provides-Extra: storage-s3
Requires-Dist: aioboto3>=15.5.0; extra == "storage-s3"
Provides-Extra: ai
Requires-Dist: openai>=1.12.0; extra == "ai"
Requires-Dist: anthropic>=0.34.0; extra == "ai"
Provides-Extra: embedding
Requires-Dist: openai>=1.12.0; extra == "embedding"
Requires-Dist: sentence-transformers>=3.0.0; extra == "embedding"
Provides-Extra: embedding-openai
Requires-Dist: openai>=1.12.0; extra == "embedding-openai"
Provides-Extra: graph-arangodb
Requires-Dist: python-arango>=8.0.1; extra == "graph-arangodb"
Provides-Extra: graph-duckdb-pgq
Requires-Dist: duckdb>=1.0.0; extra == "graph-duckdb-pgq"
Provides-Extra: graph-neo4j
Requires-Dist: neo4j>=5.22.0; extra == "graph-neo4j"
Provides-Extra: llm
Requires-Dist: openai>=1.12.0; extra == "llm"
Requires-Dist: anthropic>=0.34.0; extra == "llm"
Provides-Extra: llm-anthropic
Requires-Dist: anthropic>=0.34.0; extra == "llm-anthropic"
Provides-Extra: llm-openai
Requires-Dist: openai>=1.12.0; extra == "llm-openai"
Provides-Extra: messaging-mailgun
Requires-Dist: httpx>=0.27.2; extra == "messaging-mailgun"
Provides-Extra: messaging-webpush
Requires-Dist: pywebpush>=1.14.0; extra == "messaging-webpush"
Provides-Extra: messaging-apns
Requires-Dist: aioapns>=3.0.0; extra == "messaging-apns"
Provides-Extra: messaging-fcm
Requires-Dist: firebase-admin>=6.5.0; extra == "messaging-fcm"
Provides-Extra: messaging-sendgrid
Requires-Dist: email-validator>=2.2.0; extra == "messaging-sendgrid"
Requires-Dist: httpx>=0.27.2; extra == "messaging-sendgrid"
Provides-Extra: messaging-twilio
Requires-Dist: httpx>=0.27.2; extra == "messaging-twilio"
Provides-Extra: nosql
Requires-Dist: motor>=3.6.0; extra == "nosql"
Requires-Dist: aioboto3>=15.5.0; extra == "nosql"
Requires-Dist: google-cloud-firestore>=2.16.0; extra == "nosql"
Provides-Extra: nosql-dynamo
Requires-Dist: aioboto3>=15.5.0; extra == "nosql-dynamo"
Provides-Extra: nosql-firestore
Requires-Dist: google-cloud-firestore>=2.16.0; extra == "nosql-firestore"
Provides-Extra: nosql-mongo
Requires-Dist: motor>=3.6.0; extra == "nosql-mongo"
Provides-Extra: queue-kafka
Requires-Dist: aiokafka>=0.10.0; extra == "queue-kafka"
Provides-Extra: queue-rabbitmq
Requires-Dist: aio-pika>=9.4.0; extra == "queue-rabbitmq"
Provides-Extra: queue-streaming
Requires-Dist: aiokafka>=0.10.0; extra == "queue-streaming"
Requires-Dist: aio-pika>=9.4.0; extra == "queue-streaming"
Provides-Extra: scheduler-gcp
Requires-Dist: google-cloud-pubsub>=2.27.1; extra == "scheduler-gcp"
Requires-Dist: google-cloud-tasks>=2.16.0; extra == "scheduler-gcp"
Provides-Extra: file-transfer
Requires-Dist: aioftp>=0.23.3; extra == "file-transfer"
Requires-Dist: asyncssh>=2.15.0; extra == "file-transfer"
Provides-Extra: vector
Requires-Dist: pinecone-client>=3.1.0; extra == "vector"
Requires-Dist: qdrant-client>=1.7.3; extra == "vector"
Requires-Dist: pgvector>=0.2.4; extra == "vector"
Requires-Dist: asyncpg>=0.31.0; extra == "vector"
Provides-Extra: vector-pinecone
Requires-Dist: pinecone-client>=3.1.0; extra == "vector-pinecone"
Provides-Extra: vector-pgvector
Requires-Dist: pgvector>=0.2.4; extra == "vector-pgvector"
Requires-Dist: asyncpg>=0.31.0; extra == "vector-pgvector"
Provides-Extra: vector-qdrant
Requires-Dist: qdrant-client>=1.7.3; extra == "vector-qdrant"
Dynamic: license-file
